openfisca_parsers/__init__.py
openfisca_parsers/formulas_parsers_2to3.py
openfisca_parsers/input_variables_extractors.py
openfisca_parsers/source_formulas_extractors.py
openfisca_parsers/scripts/__init__.py
openfisca_parsers/scripts/datatrees_to_json.py
openfisca_parsers/scripts/extract_input_variables.py
openfisca_parsers/scripts/extract_source_formulas.py
openfisca_parsers/scripts/extract_variables_tree.py
OpenFisca_Parsers-1.0.2.dist-info/top_level.txt
OpenFisca_Parsers-1.0.2.dist-info/METADATA
OpenFisca_Parsers-1.0.2.dist-info/DESCRIPTION.rst
OpenFisca_Parsers-1.0.2.dist-info/metadata.json
OpenFisca_Parsers-1.0.2.dist-info/WHEEL
OpenFisca_Parsers-1.0.2.dist-info/RECORD
