Metadata-Version: 2.0
Name: OpenFisca-Parsers
Version: 1.0.2
Summary: Lexers, parsers, compilers, etc for OpenFisca source code
Home-page: https://github.com/openfisca/openfisca-parsers
Author: OpenFisca Team
Author-email: contact@openfisca.fr
License: http://www.fsf.org/licensing/licenses/agpl-3.0.html
Keywords: benefit compiler lexer microsimulation parser social tax
Platform: UNKNOWN
Classifier: Development Status :: 2 - Pre-Alpha
Classifier: License :: OSI Approved :: GNU Affero General Public License v3
Classifier: Operating System :: POSIX
Classifier: Programming Language :: Python
Classifier: Topic :: Scientific/Engineering :: Information Analysis
Requires-Dist: Biryani[datetimeconv] (>=0.10.1)
Requires-Dist: numpy (>=1.11)
